enphase_api/cloud/__init__.py
enphase_api/cloud/authentication.py
enphase_api/local/__init__.py
enphase_api/local/gateway.py
enphase_api/local/ignore_hostname_adapter.py
Enphase_API-1.0.0.dist-info/METADATA
Enphase_API-1.0.0.dist-info/WHEEL
Enphase_API-1.0.0.dist-info/top_level.txt
Enphase_API-1.0.0.dist-info/RECORD
