Metadata-Version: 2.1
Name: Enphase-API
Version: 1.0.0
Summary: An unofficial Enphase® API that predominantly focuses on the local API.
Author: Matthew1471! (https://Matthew1471.co.uk/Contact.php)
Maintainer: Matthew1471! (https://Matthew1471.co.uk/Contact.php)
License: License :: OSI Approved :: GNU General Public License v3 (GPLv3)
Project-URL: Homepage, https://github.com/Matthew1471/Enphase-API
Project-URL: Bug Reports, https://github.com/Matthew1471/Enphase-API/issues
Project-URL: Documentation, https://github.com/Matthew1471/Enphase-API/tree/main/Documentation
Project-URL: Say Thanks!, https://Matthew1471.co.uk/Contact.php
Project-URL: Source, https://github.com/Matthew1471/Enphase-API
Keywords: Enphase,Envoy,Gateway,Solar,Microinverters,Production,Generation,Sun
Classifier: Development Status :: 4 - Beta
Classifier: Intended Audience :: Developers
Classifier: Operating System :: OS Independent
Classifier: Topic :: Documentation
Classifier: Topic :: Software Development :: Documentation
Classifier: Topic :: Software Development :: Embedded Systems
Classifier: Topic :: Software Development :: Libraries
Classifier: Topic :: Software Development :: Libraries :: Python Modules
Classifier: Topic :: System :: Hardware
Classifier: Topic :: System :: Monitoring
Classifier: Topic :: System :: Networking :: Monitoring
Classifier: Topic :: System :: Power (UPS)
Classifier: License :: OSI Approved :: GNU General Public License v3 (GPLv3)
Classifier: Programming Language :: Python
Classifier: Programming Language :: Python :: 3
Classifier: Programming Language :: Python :: 3 :: Only
Classifier: Programming Language :: Python :: 3.7
Classifier: Programming Language :: Python :: 3.8
Classifier: Programming Language :: Python :: 3.9
Classifier: Programming Language :: Python :: 3.10
Classifier: Programming Language :: Python :: 3.11
Classifier: Programming Language :: Python :: 3.12
Requires-Python: >=3.7
Requires-Dist: requests
Requires-Dist: PyJWT
Provides-Extra: dev
Requires-Dist: pillow ; extra == 'dev'
Requires-Dist: unicorn-hat-sim ; extra == 'dev'
